gaspy/GumnutAssembler.py
gaspy/GumnutExceptions.py
gaspy/__init__.py
src/GumnutAssembler.py
src/GumnutExceptions.py
src/__init__.py
gaspy-1.0.3.dist-info/LICENSE
gaspy-1.0.3.dist-info/METADATA
gaspy-1.0.3.dist-info/WHEEL
gaspy-1.0.3.dist-info/entry_points.txt
gaspy-1.0.3.dist-info/top_level.txt
gaspy-1.0.3.dist-info/RECORD
