Metadata-Version: 2.1
Name: gaspy
Version: 1.0.3
Summary: Gumnut Assembler written in Python
Home-page: https://github.com/bwiessneth/gaspy
Author: Benjamin Wiessneth
Author-email: b.wiessneth@gmail.com
License: UNKNOWN
Platform: UNKNOWN
Classifier: Programming Language :: Python :: 3
Classifier: License :: OSI Approved :: GNU General Public License v3 or later (GPLv3+)
Classifier: Operating System :: OS Independent
Requires-Python: >=3.6
